simplecep/__init__.py
simplecep/cepaddress.py
simplecep/exceptions.py
simplecep/resolver.py
simplecep/utils.py
simplecep/providers/__init__.py
simplecep/providers/commons.py
simplecep/providers/correios_sigep.py
simplecep/providers/republicavirtual.py
simplecep/providers/viacep.py
simplecep-0.1.1.dist-info/LICENSE
simplecep-0.1.1.dist-info/METADATA
simplecep-0.1.1.dist-info/WHEEL
simplecep-0.1.1.dist-info/top_level.txt
simplecep-0.1.1.dist-info/zip-safe
simplecep-0.1.1.dist-info/RECORD
