Metadata-Version: 2.1
Name: simplecep
Version: 0.1.1
Summary: Fetch CEP addresses consistently using Correios API, third-party APIs as fallbacks and cache the results.
Home-page: https://github.com/cauethenorio/simplecep
Author: Cauê Thenório
Author-email: caue@thenorio.com.br
License: MIT
Keywords: cep,correios,brasil,endereço
Platform: UNKNOWN
Classifier: Operating System :: POSIX
Classifier: Programming Language :: Python :: 3
Classifier: Programming Language :: Python :: 3.6
Classifier: Programming Language :: Python :: 3.7
Classifier: Programming Language :: Python :: 3.8
Classifier: Programming Language :: Python :: 3.9
Classifier: Programming Language :: Python :: 3.10
Classifier: Intended Audience :: Developers
Classifier: License :: OSI Approved :: MIT License
Classifier: Intended Audience :: Developers
Classifier: Natural Language :: English
Requires-Python: >=3.6
